{
  "project_info": {
    "project_number": "205098330268",
    "project_id": "taekwondoattendance-17a51",
    "storage_bucket": "taekwondoattendance-17a51.firebasestorage.app"
  },
  "client": [
    {
      "client_info": {
        "mobilesdk_app_id": "1:205098330268:android:f50d2d6781d44c47a56559",
        "android_client_info": {
          "package_name": "com.pranav.attendecetaker"
        }
      },
      "oauth_client": [],
      "api_key": [
        {
          "current_key": "AIzaSyBIQyjGRIK7CJlHBkYnKZNGkUbuNUEBfI8"
        }
      ],
      "services": {
        "appinvite_service": {
          "other_platform_oauth_client": []
        }
      }
    }
  ],
  "configuration_version": "1"
}